setup.cfg
setup.py
bin/logtrails
bin/logtrails-queue-dump
logtrails/__init__.py
logtrails/config.py
logtrails/logreader.py
logtrails/queue.py
logtrails.egg-info/PKG-INFO
logtrails.egg-info/SOURCES.txt
logtrails.egg-info/dependency_links.txt
logtrails.egg-info/requires.txt
logtrails.egg-info/top_level.txt