Metadata-Version: 1.0
Name: logtrails
Version: 1.0.1
Summary: Logging message queue processors
Home-page: https://github.com/hile/logtrails/
Author: Ilkka Tuohela
Author-email: hile@iki.fi
License: PSF
Keywords: logging redis pubsub message processor
Platform: UNKNOWN
